assets/__init__.py
assets/advanced_regression/__init__.py
assets/advanced_regression/advanced_regression_data_manager.py
assets/advanced_regression/advanced_regression_model_manager.py
assets/advanced_regression/configs/__init__.py
assets/advanced_regression/configs/advanced_regression_forecast_config.py
assets/advanced_regression/configs/advanced_regression_train_config.py
assets/basic_regression/__init__.py
assets/basic_regression/basic_regression_data_manager.py
assets/basic_regression/basic_regression_model_manager.py
assets/basic_regression/configs/__init__.py
assets/basic_regression/configs/basic_regression_custom_pipeline_config.py
assets/basic_regression/configs/basic_regression_feature_engineering_config.py
assets/basic_regression/configs/basic_regression_forecast_config.py
assets/basic_regression/configs/basic_regression_reuse_features_and_train_config.py
assets/basic_regression/configs/basic_regression_train_config.py
assets/basic_regression/configs/basic_regression_train_step_config.py
assets/classification/__init__.py
assets/classification/classification_data_manager.py
assets/classification/classification_feature_engineering.py
assets/classification/classification_model_manager.py
assets/classification/classification_visualizations.py
assets/classification/configs/__init__.py
assets/classification/configs/classification_feature_engineering_config.py
assets/classification/configs/classification_forecast_config.py
assets/classification/configs/classification_reuse_features_and_train_config.py
assets/classification/configs/classification_train_config.py
assets/crash_course/__init__.py
assets/crash_course/crash_course_data_manager.py
assets/crash_course/crash_course_model_manager.py
assets/crash_course/configs/crash_course_forecast_config.json
assets/crash_course/configs/crash_course_train_config.json
assets/spark_classification/__init__.py
assets/spark_classification/spark_classification_data_manager.py
mlapp-0.1.6.1.dist-info/LICENSE
mlapp-0.1.6.1.dist-info/METADATA
mlapp-0.1.6.1.dist-info/WHEEL
mlapp-0.1.6.1.dist-info/entry_points.txt
mlapp-0.1.6.1.dist-info/top_level.txt
mlapp-0.1.6.1.dist-info/RECORD
