Metadata-Version: 2.1
Name: mlapp
Version: 0.1.6.1
Summary: IBM Services Framework for ML Applications Python 3 framework for building robust, production-ready machine learning applications. Official ML accelerator within the larger RAD-ML methodology.
Home-page: https://github.com/ibm/mlapp
Author: IBM
Author-email: tomer.galula@ibm.com, tal.waitzenberg@ibm.com, michael.chein@ibm.com, erez.nardia@ibm.com, annaelle.cohen@ibm.com, katzn@us.ibm.com
License: Apache License 2.0
Project-URL: Bug Reports, https://github.com/ibm/mlapp/issues
Project-URL: Wiki Page, https://mlapp-docs.s3-web.us-south.cloud-object-storage.appdomain.cloud
Project-URL: Crash Course, https://mlapp-docs.s3-web.us-south.cloud-object-storage.appdomain.cloud/crash-course/introduction
Project-URL: Source, https://github.com/ibm/mlapp
Keywords: mlapp,ibm,machine-learning,auto-ml
Platform: UNKNOWN
Classifier: Intended Audience :: Developers
Classifier: Programming Language :: Python :: 3
Classifier: Programming Language :: Python :: 3.6
Classifier: Programming Language :: Python :: 3.7
Classifier: Programming Language :: Python :: 3.8
Classifier: Programming Language :: Python :: 3.9
Classifier: License :: OSI Approved :: Apache Software License
Requires-Python: >=3.6
Requires-Dist: pandas
Requires-Dist: scipy
Requires-Dist: numpy (>=1.16.5)
Requires-Dist: scikit-learn
Requires-Dist: matplotlib
Requires-Dist: environs
Requires-Dist: click
Requires-Dist: tabulate
Requires-Dist: requests
Requires-Dist: urllib3
Requires-Dist: sqlalchemy (<=1.3.22)
Requires-Dist: jsonschema
Provides-Extra: aml
Requires-Dist: azureml-sdk ; extra == 'aml'
Provides-Extra: azure-servicebus
Requires-Dist: azure-servicebus (<=0.50.3) ; extra == 'azure-servicebus'
Provides-Extra: azure-storage-blob
Requires-Dist: azure-storage-blob (<=2.1.0) ; extra == 'azure-storage-blob'
Provides-Extra: boto3
Requires-Dist: boto3 ; extra == 'boto3'
Provides-Extra: cp
Requires-Dist: pika ; extra == 'cp'
Requires-Dist: pg8000 (<=1.16.5) ; extra == 'cp'
Requires-Dist: minio ; extra == 'cp'
Provides-Extra: ibm-boto3
Requires-Dist: ibm-cos-sdk ; extra == 'ibm-boto3'
Provides-Extra: kafka
Requires-Dist: kafka-python ; extra == 'kafka'
Provides-Extra: kafka-kerberos
Requires-Dist: confluent-kafka ; extra == 'kafka-kerberos'
Provides-Extra: livy
Requires-Dist: livy ; extra == 'livy'
Provides-Extra: minio
Requires-Dist: minio ; extra == 'minio'
Provides-Extra: mssql
Requires-Dist: pyodbc ; extra == 'mssql'
Provides-Extra: mysql
Requires-Dist: PyMySQL ; extra == 'mysql'
Provides-Extra: postgres
Requires-Dist: pg8000 (<=1.16.5) ; extra == 'postgres'
Provides-Extra: pyspark
Requires-Dist: pyspark ; extra == 'pyspark'
Provides-Extra: rabbitmq
Requires-Dist: pika ; extra == 'rabbitmq'
Provides-Extra: sm
Requires-Dist: sagemaker ; extra == 'sm'
Requires-Dist: sagemaker-training ; extra == 'sm'
Provides-Extra: snowflake
Requires-Dist: snowflake-sqlalchemy ; extra == 'snowflake'
